AUTHORS
LICENSE
MANIFEST.in
README.rst
setup.py
pstatus/__init__.py
pstatus/main.py
pstatus/models.py
pstatus/os.py
pstatus.egg-info/PKG-INFO
pstatus.egg-info/SOURCES.txt
pstatus.egg-info/dependency_links.txt
pstatus.egg-info/top_level.txt