Metadata-Version: 1.1
Name: pstatus
Version: 1.1.2
Summary: Process Status Code Helper
Home-page: https://github.com/mkomitee/pstatus
Author: Michael Komitee
Author-email: mkomitee@gmail.com
License: Copyright (c) 2013, Michael Komitee
